{
    "videos": [
        { "title": "Blaseinkontinänz @ Bierhübeli Bern", "link": "XpXBFqZxJG8", "start": 1114, "end": 1187 },
        { "title": "Bluetwurscht @ Bierhübeli Bern", "link": "XpXBFqZxJG8", "start": 1216, "end": 1314 },
        { "title": "Aaaretouche @ Bierhübeli Bern", "link": "XpXBFqZxJG8", "start": 1338, "end": 1458 },
        { "title": "Hoselade @ Mühli Hunzike", "link": "U369qnYQu2g", "start": 0, "end": 55 },
        { "title": "Bananeschale @ Mühli Hunzike", "link": "FYE7N_FdYNE", "start": 0, "end": 48 },
        { "title": "Chopflos @ Kufa Lyss", "link": "s2wVPSJQgrg", "start": 596, "end": 666 },
        { "title": "Fuesspiuz @ Mühli Hunzike", "link": "0LCkk5aKa88", "start": 289, "end": 382 },
        { "title": "Duurwäue @ Mühli Hunzike", "link": "0LCkk5aKa88", "start": 407, "end": 494 },
        { "title": "Handbürschtmaschine @ Music Days Stäffisburg", "link": "Lcsi8OFMhlU", "start": 4, "end": 85 },
        { "title": "Basilikum @ Music Days Stäffisburg", "link": "Lcsi8OFMhlU", "start": 107, "end": 188 },
        { "title": "Huusufgabe @ Music Days Stäffisburg", "link": "Lcsi8OFMhlU", "start": 213, "end": 289 },
        { "title": "Hamburger @ Mani Matter Festival", "link": "YLrriry3NMc", "start": 0, "end": 80 },
        { "title": "Dünnpfiff @ Mani Matter Festival", "link": "YLrriry3NMc", "start": 105, "end": 186  },
        { "title": "Gebärdesprachlied @ Mani Matter Festival", "link": "YLrriry3NMc", "start": 215, "end": 307  },
        { "title": "Murat Yakin @ Presswerk Arbon", "link": "mqXhMFbleU8", "start": 1093, "end": 1207  },
        { "title": "Wiehnachte @ Presswerk Arbon", "link": "mqXhMFbleU8", "start": 1239, "end": 1362  },
        { "title": "Influencer,Schiifahre, Wandere @ Presswerk Arbon", "link": "mqXhMFbleU8", "start": 1393, "end": 1542  },
        { "title": "Beat Feuz, Wandererer @ Casino Theater Burgdorf", "link": "YDMBY1UB_SY", "start": 159, "end": 312  },
        { "title": "Siuberzibelä, Walliselle @ Mokka Thun", "link": "6GvCHsR0zcw", "start": 25, "end": 135  },
        { "title": "Pfifoltere @ Mokka Thun", "link": "6GvCHsR0zcw", "start": 158, "end": 245  },
        { "title": "Bärner Müntschi @ Mokka Thun", "link": "6GvCHsR0zcw", "start": 270, "end": 424  },
        { "title": "Öufi-Boot @ Hafefest Solothurn", "link": "67Hhp2BnWlc", "start": 29, "end": 191  },
        { "title": "Rahmschnitzu @ Gurtenfestival", "link": "4IE3RryPqWo", "start": 0, "end": 42  },
        { "title": "Schwarzwasser @ Gurtenfestival", "link": "4IE3RryPqWo", "start": 67, "end": 119  },
        { "title": "Rittigampfi @ Gurtenfestival", "link": "4IE3RryPqWo", "start": 142, "end": 186  },
        { "title": "Entertainer @ Bierhübeli Bern", "link": "nnr2CSXUwAU", "start": 9, "end": 84  },
        { "title": "Highheels @ Bierhübeli Bern", "link": "nnr2CSXUwAU", "start": 114, "end": 189  },
        { "title": "Haudimaa @ Bierhübeli Bern", "link": "nnr2CSXUwAU", "start": 216, "end": 307  }
    ]
}